pydantic_graph_neo4j_persistence/__init__.py
pydantic_graph_neo4j_persistence/neo4j_state_persistence.py
pydantic_graph_neo4j_persistence-0.1.6.dist-info/METADATA
pydantic_graph_neo4j_persistence-0.1.6.dist-info/WHEEL
pydantic_graph_neo4j_persistence-0.1.6.dist-info/licenses/LICENSE
pydantic_graph_neo4j_persistence-0.1.6.dist-info/RECORD
