Metadata-Version: 2.4
Name: pydantic-graph-neo4j-persistence
Version: 0.1.6
Summary: Neo4j persistence adapter for Pydantic Graph
Project-URL: Homepage, https://github.com/Goduu/pydantic_graph.neo4j_persistence
Project-URL: Source, https://github.com/Goduu/pydantic_graph.neo4j_persistence
Author-email: Goduu <idcangussu@hotmail.com>
License: MIT
License-File: LICENSE
Classifier: Environment :: Console
Classifier: Environment :: MacOS X
Classifier: Intended Audience :: Developers
Classifier: Intended Audience :: Information Technology
Classifier: Intended Audience :: System Administrators
Classifier: Programming Language :: Python
Classifier: Programming Language :: Python :: 3
Classifier: Programming Language :: Python :: 3 :: Only
Classifier: Programming Language :: Python :: 3.9
Classifier: Programming Language :: Python :: 3.10
Classifier: Programming Language :: Python :: 3.11
Classifier: Programming Language :: Python :: 3.12
Classifier: Programming Language :: Python :: 3.13
Classifier: Topic :: Internet
Classifier: Topic :: Software Development :: Libraries :: Python Modules
Requires-Python: >=3.9
Requires-Dist: neo4j>=5.0
Requires-Dist: pydantic-ai>=0.0.42
Requires-Dist: pydantic-graph>=0.0.42
Requires-Dist: pydantic>=2.0
